chyllonge/__init__.py
chyllonge/api.py
chyllonge-1.1.1.dist-info/LICENSE.txt
chyllonge-1.1.1.dist-info/WHEEL
chyllonge-1.1.1.dist-info/METADATA
chyllonge-1.1.1.dist-info/RECORD
