Metadata-Version: 2.1
Name: chyllonge
Version: 1.1.1
Summary: A Python 3.8+ implementation of the challonge.com API.
Keywords: challonge
Author-email: Alex Fredrickson <alex.q.fredrickson@gmail.com>
Maintainer-email: Alex Fredrickson <alex.q.fredrickson@gmail.com>
Requires-Python: >=3.8
Classifier: Development Status :: 4 - Beta
Classifier: Programming Language :: Python :: 3.8
Classifier: Programming Language :: Python :: 3.9
Classifier: Programming Language :: Python :: 3.10
Classifier: Programming Language :: Python :: 3.11
Requires-Dist: tzlocal>=5.2
Requires-Dist: requests>=2.31.0
Project-URL: Bug Tracker, https://www.github.com/alexqfredrickson/chyllonge/issues
Project-URL: Homepage, https://www.github.com/alexqfredrickson/chyllonge
Project-URL: Repository, https://www.github.com/alexqfredrickson/chyllonge
